codeprofile/__init__.py
codeprofile/__main__.py
codeprofile/profiler.py
codeprofile-1.0.2.dist-info/LICENSE
codeprofile-1.0.2.dist-info/METADATA
codeprofile-1.0.2.dist-info/WHEEL
codeprofile-1.0.2.dist-info/top_level.txt
codeprofile-1.0.2.dist-info/zip-safe
codeprofile-1.0.2.dist-info/RECORD
