Metadata-Version: 2.1
Name: codeprofile
Version: 1.0.2
Summary: Profiling CPU usage for blocks of code
Home-page: https://github.com/mukatee/python-code-profile
Author: Teemu Kanstrén
Author-email: tkanstren@protonmail.com
License: MIT
Keywords: profiling,monitoring,performance,trace
Platform: UNKNOWN
Classifier: License :: OSI Approved :: MIT License
Classifier: Programming Language :: Python :: 3.6
Classifier: Programming Language :: Python :: 3.7
Classifier: Programming Language :: Python :: 3.8
Classifier: Programming Language :: Python :: 3.9
Classifier: Development Status :: 5 - Production/Stable
Classifier: Topic :: Software Development :: Testing
Classifier: Topic :: Software Development
